AUTHORS.md
CHANGELOG.md
CONTRIBUTING.md
LICENSE
MANIFEST.in
README.md
setup.cfg
setup.py
docs/Makefile
docs/conf.py
docs/make.bat
tests/__init__.py
tests/integration/__init__.py
tests/integration/test_anyconfig.py
tests/unit/__init__.py
tests/unit/conftest.py
tests/unit/test_config_loading_and_dumping.py
tests/unit/test_engine_detection.py
tests/unit/test_fuzz.py
tests/unit/test_init.py
tests/unit/test_vault_auth.py
tests/unit/file_handling_tests/__init__.py
tests/unit/file_handling_tests/conftest.py
tests/unit/file_handling_tests/test_config_secret_file_usage.py
tests/unit/file_handling_tests/test_direct_secret_file_usage.py
tests/unit/file_handling_tests/test_fuzz_secret_file.py
vault_anyconfig/__init__.py
vault_anyconfig/cli.py
vault_anyconfig/vault_anyconfig.py
vault_anyconfig.egg-info/PKG-INFO
vault_anyconfig.egg-info/SOURCES.txt
vault_anyconfig.egg-info/dependency_links.txt
vault_anyconfig.egg-info/entry_points.txt
vault_anyconfig.egg-info/not-zip-safe
vault_anyconfig.egg-info/requires.txt
vault_anyconfig.egg-info/top_level.txt