Metadata-Version: 2.1
Name: vault-anyconfig
Version: 0.3.1
Summary: Describe in a short sentence your Python package.
Home-page: https://github.com/tomtom-international/vault-anyconfig
Author: Eugene Davis
Author-email: eugene.davis@tomtom.com
License: Apache Software License 2.0
Keywords: vault_anyconfig
Platform: UNKNOWN
Classifier: Programming Language :: Python :: 3
Classifier: Intended Audience :: Developers
Classifier: License :: OSI Approved :: Apache Software License
Classifier: Natural Language :: English
Classifier: Programming Language :: Python :: 3
Classifier: Programming Language :: Python :: 3.5
Classifier: Programming Language :: Python :: 3.6
Classifier: Programming Language :: Python :: 3.7
Classifier: Environment :: Console
Classifier: Operating System :: OS Independent
